MANIFEST.in
README.txt
setup.cfg
setup.nsi
setup.py
sy85tools.kpf
doc/SY85-disk-files-list.txt
doc/SY85-disk-files.txt
doc/SY85-sysex-messages.txt
doc/SY85WaveReader.vbs
doc/wave-format-85.txt
doc/waveform-cards.txt
examples/CO_Sable.syx
examples/InitPerf.syx
examples/InitVce.syx
examples/PF_CO_Dream.dat
examples/PF_KY_Piano.dat
examples/SP_Makro_v1.1.syx
examples/SP_Makro_v1.2.syx
examples/SP_Movie_v1.1.syx
examples/SP_Movie_v1.2.syx
examples/VC_SP_Makro.dat
examples/VC_SP_Movie.dat
examples/fact-set.g01
examples/sy85-fact.syx
examples/tg500-fact.syx
scripts/genlistings
scripts/sy85info
scripts/sy85sxtool
sy85/__init__.py
sy85/binreader.py
sy85/binutils.py
sy85/bulktypes.py
sy85/constants.py
sy85/sysex.py
sy85/sywave.py
sy85/converters/__init__.py
sy85/converters/base.py
sy85/converters/smf.py
sy85/data/__init__.py
sy85/data/patches.py
sy85/data/voice.py
sy85/scripts/__init__.py
sy85/scripts/sy85all.py
sy85/scripts/sy85sxtool.py
sy85tools.egg-info/PKG-INFO
sy85tools.egg-info/SOURCES.txt
sy85tools.egg-info/dependency_links.txt
sy85tools.egg-info/top_level.txt
sy85tools.egg-info/zip-safe