Metadata-Version: 1.0
Name: sy85tools
Version: 0.2.1a
Summary: Collection of tools to handle MIDI sysex and other files for the Yamaha SY85
Home-page: http://chrisarndt.de/projects/sy85tools/
Author: Christopher Arndt
Author-email: chris@chrisarndt.de
License: MIT license
Download-URL: http://chrisarndt.de/projects/sy85tools/download/
Keywords: midi,sysex
Platform: POSIX
Platform: Windows
Platform: MacOS X
Classifier: Development Status :: 3 - Alpha
Classifier: Environment :: Console
Classifier: Intended Audience :: Developers
Classifier: Intended Audience :: Other Audience
Classifier: License :: OSI Approved :: MIT License
Classifier: Operating System :: Microsoft :: Windows
Classifier: Operating System :: POSIX
Classifier: Operating System :: MacOS :: MacOS X
Classifier: Programming Language :: Python
Classifier: Topic :: Multimedia :: Sound/Audio :: Conversion
Classifier: Topic :: Multimedia :: Sound/Audio :: MIDI
Classifier: Topic :: Software Development :: Libraries :: Python Modules
